{
  "trained_at": "2026-04-24T12:05:46.909108",
  "n_samples": 8240,
  "n_features": 37,
  "feature_names": [
    "age",
    "gender",
    "education",
    "income_ratio",
    "bmi",
    "waist_circumference",
    "hba1c",
    "fasting_glucose",
    "total_cholesterol",
    "hdl_cholesterol",
    "smoked_100",
    "current_smoker",
    "vigorous_work",
    "moderate_work",
    "vigorous_rec",
    "moderate_rec",
    "sedentary_minutes",
    "diabetes_indicator",
    "race_ethnicity_2.0",
    "race_ethnicity_3.0",
    "race_ethnicity_4.0",
    "race_ethnicity_6.0",
    "race_ethnicity_7.0",
    "smoking_status_Former",
    "smoking_status_Never",
    "activity_level_Low",
    "activity_level_Moderate",
    "activity_level_Sedentary",
    "bmi_category_Obese_I",
    "bmi_category_Obese_II",
    "bmi_category_Obese_III",
    "bmi_category_Overweight",
    "bmi_category_Underweight",
    "age_group_36-45",
    "age_group_46-55",
    "age_group_56-65",
    "age_group_65+"
  ],
  "params": {
    "n_estimators": 500,
    "max_depth": 5,
    "learning_rate": 0.05,
    "subsample": 0.8,
    "colsample_bytree": 0.8,
    "min_child_weight": 5,
    "gamma": 0.1,
    "reg_alpha": 0.05,
    "reg_lambda": 2.0,
    "random_state": 42,
    "early_stopping_rounds": 30,
    "scale_pos_weight": "auto"
  },
  "best_iteration": 38,
  "model_type": "Hypertension Risk Model",
  "note": "BP readings excluded from features \u2014 preventive risk model",
  "scale_pos_weight": 3.524986271279517,
  "threshold": 0.3
}